README.md
setup.py
acenv/__init__.py
acenv.egg-info/PKG-INFO
acenv.egg-info/SOURCES.txt
acenv.egg-info/dependency_links.txt
acenv.egg-info/top_level.txt
acenv/engine/__init__.py
acenv/engine/pn/__init__.py
acenv/engine/pn/func.py
acenv/engine/pn/pn.py
acenv/engine/pn/pntesting.py
acenv/engine/rn/__init__.py
acenv/engine/rn/func.py
acenv/engine/rn/rn.py
acenv/engine/rn/rntesting.py
acenv/ex/__init__.py
acenv/ex/ex.py
acenv/ex/extesting.py
acenv/ex/func.py
acenv/ex/tr.py