Metadata-Version: 2.1
Name: acenv
Version: 0.1.4
Summary: Algebraic Calculation Environment for python
Home-page: UNKNOWN
Author: Andrea Viganò
Author-email: vigano02aceproject@gmail.com
License: MIT
Platform: UNKNOWN
Classifier: Development Status :: 4 - Beta
Classifier: Programming Language :: Python :: 3
Classifier: License :: OSI Approved :: MIT License
Classifier: Operating System :: OS Independent
Requires-Python: >=3.7
